flexible_clustering_tree/__init__.py
flexible_clustering_tree/base_clustering.py
flexible_clustering_tree/interface.py
flexible_clustering_tree/logger.py
flexible_clustering_tree/models.py
flexible_clustering_tree/string_matching.py
flexible_clustering_tree/utils.py
flexible_clustering_tree/__pycache__/__init__.cpython-36.pyc
flexible_clustering_tree/__pycache__/base_clustering.cpython-36.pyc
flexible_clustering_tree/__pycache__/interface.cpython-36.pyc
flexible_clustering_tree/__pycache__/logger.cpython-36.pyc
flexible_clustering_tree/__pycache__/models.cpython-36.pyc
flexible_clustering_tree/__pycache__/string_matching.cpython-36.pyc
flexible_clustering_tree/__pycache__/utils.cpython-36.pyc
flexible_clustering_tree/resources/__init__.py
flexible_clustering_tree/resources/tree_template.html
flexible_clustering_tree-0.21.dist-info/LICENSE.txt
flexible_clustering_tree-0.21.dist-info/METADATA
flexible_clustering_tree-0.21.dist-info/WHEEL
flexible_clustering_tree-0.21.dist-info/top_level.txt
flexible_clustering_tree-0.21.dist-info/RECORD
