Metadata-Version: 2.1
Name: flexible-clustering-tree
Version: 0.21
Summary: easy interface for ensemble clustering
Home-page: https://github.com/Kensuke-Mitsuzawa/flexible_clustering_tree
Author: Kensuke Mitsuzawa
Author-email: kensuke.mit@gmail.com
License: UNKNOWN
Platform: UNKNOWN
Requires-Dist: sqlitedict
Requires-Dist: scipy
Requires-Dist: numpy
Requires-Dist: scikit-learn
Requires-Dist: hdbscan
Requires-Dist: pyexcelerate
Requires-Dist: jinja2
Requires-Dist: pypandoc
